MANIFEST.in
README.rst
setup.py
blend/__init__.py
blend/__init__.pyc
blend/config.py
blend/config.pyc
blend/bcc/__init__.py
blend/bcc/__init__.pyc
blend/cloudman/__init__.py
blend/cloudman/__init__.pyc
blend/cloudman/launch.py
blend/cloudman/launch.pyc
blend/galaxy/__init__.py
blend/galaxy/__init__.pyc
blend/galaxy/client.py
blend/galaxy/client.pyc
blend/galaxy/datasets/__init__.py
blend/galaxy/datasets/__init__.pyc
blend/galaxy/histories/__init__.py
blend/galaxy/histories/__init__.pyc
blend/galaxy/libraries/__init__.py
blend/galaxy/libraries/__init__.pyc
blend/galaxy/libraries/client.pyc
blend/galaxy/users/__init__.py
blend/galaxy/users/__init__.pyc
blend/galaxy/workflows/__init__.py
blend/galaxy/workflows/__init__.pyc
blend_lib.egg-info/PKG-INFO
blend_lib.egg-info/SOURCES.txt
blend_lib.egg-info/dependency_links.txt
blend_lib.egg-info/requires.txt
blend_lib.egg-info/top_level.txt
docs/.DS_Store
docs/Makefile
docs/conf.py
docs/index.rst
docs/_build/.DS_Store
docs/_build/doctrees/environment.pickle
docs/_build/doctrees/galaxy.doctree
docs/_build/doctrees/index.doctree
docs/_build/doctrees/api_docs/galaxy.doctree
docs/_build/doctrees/api_docs/bcc/all.doctree
docs/_build/doctrees/api_docs/cloudman/all.doctree
docs/_build/doctrees/api_docs/galaxy/all.doctree
docs/_build/html/.buildinfo
docs/_build/html/genindex.html
docs/_build/html/index.html
docs/_build/html/objects.inv
docs/_build/html/py-modindex.html
docs/_build/html/search.html
docs/_build/html/searchindex.js
docs/_build/html/_modules/index.html
docs/_build/html/_modules/blend/cloudman.html
docs/_build/html/_modules/blend/galaxy.html
docs/_build/html/_modules/blend/cloudman/launch.html
docs/_build/html/_modules/blend/galaxy/datasets.html
docs/_build/html/_modules/blend/galaxy/histories.html
docs/_build/html/_modules/blend/galaxy/libraries.html
docs/_build/html/_modules/blend/galaxy/users.html
docs/_build/html/_modules/blend/galaxy/workflows.html
docs/_build/html/_sources/index.txt
docs/_build/html/_sources/api_docs/bcc/all.txt
docs/_build/html/_sources/api_docs/cloudman/all.txt
docs/_build/html/_sources/api_docs/galaxy/all.txt
docs/_build/html/_static/ajax-loader.gif
