Metadata-Version: 1.0
Name: blend-lib
Version: 0.12
Summary: BioCloudCentral.org, CloudMan, and Galaxy API library
Home-page: http://blend.readthedocs.org/
Author: Enis Afgan
Author-email: afgane@gmail.com
License: MIT
Platform: Posix; MacOS X; Windows
Classifier: Development Status :: 3 - Alpha
Classifier: Intended Audience :: Developers
Classifier: License :: OSI Approved :: MIT License
Classifier: Operating System :: OS Independent
Classifier: Topic :: Internet
Classifier: Programming Language :: Python :: 2
Classifier: Programming Language :: Python :: 2.6
Classifier: Programming Language :: Python :: 2.7
